pler/__init__.py
pler/__main__.py
pler/cli.py
python_pler-0.1.2.dist-info/METADATA
python_pler-0.1.2.dist-info/WHEEL
python_pler-0.1.2.dist-info/entry_points.txt
python_pler-0.1.2.dist-info/top_level.txt
python_pler-0.1.2.dist-info/RECORD
