Metadata-Version: 2.4
Name: python-pler
Version: 0.1.2
Summary: Pler - Probe and Cloudflare Filter Tool
Author-email: Justakazh <akaswisnuaji@gmail.com>
Requires-Python: >=3.8
Requires-Dist: requests
